{
    "Name": "M113 chassis",
    "Type": "Chassis",
    "Template": "RigidChassis",

    "Components": [
        {
            "Centroidal Frame": {
                "Location": [ -2.006, 0, 0.406 ],
                "Orientation": [ 1, 0, 0, 0 ]
            },
            "Mass": 5489.24,
            "Moments of Inertia": [ 1786.92, 10449.67, 10721.22 ],
            "Products of Inertia": [ 0, 0, 0 ],
            "Void": false
        }
    ],

    "Driver Position": {
        "Location": [ 0, 0.5, 1.2 ],
        "Orientation": [ 1, 0, 0, 0 ]
    },

    "Contact": {
        "Materials": [
            {
                "Coefficient of Friction": 0.7,
                "Coefficient of Restitution": 0.1,

                "Properties": {
                    "Young Modulus": 1e7,
                    "Poisson Ratio": 0.3
                },

                "Coefficients": {
                    "Normal Stiffness": 2e5,
                    "Normal Damping": 40.0,
                    "Tangential Stiffness": 2e5,
                    "Tangential Damping": 20.0
                }
            }
        ],

        "Shapes": [
            {
                "Type": "HULL",
                "Filename": "M113/Chassis_Hulls.obj",
                "Material Index": 0
            }
        ]
    },

    "Visualization": {
        "Mesh": "M113/Chassis_Hulls.obj"
    }
}
