{
    "Name": "M113 chassis",
    "Type": "Chassis",
    "Template": "RigidChassis",

    "Components": [
        {
            "Centroidal Frame": {
                "Location": [ -2.006, 0, 0.406 ],
                "Orientation": [ 1, 0, 0, 0 ]
            },
            "Mass": 7819.24,
            "Moments of Inertia": [ 13983.08, 27287.61, 28805.57 ],
            "Products of Inertia": [ 0, 0, 0 ],
            "Void": false
        }
    ],

    "Driver Position": {
        "Location": [ 0, 0.5, 1.2 ],
        "Orientation": [ 1, 0, 0, 0 ]
    },

    "Visualization": {
        "Mesh": "M113/meshes/Chassis.obj",

        "Primitives": [
            {
                "Type": "SPHERE",
                "Location": [ -2.006, 0, 0.406 ],
                "Radius": 0.1
            },
            {
                "Type": "CYLINDER",
                "Location": [ -2.006, 0, 0.406 ],
                "Axis": [ 0, 1, 0 ],
                "Radius": 0.02,
                "Length": 0.6
            },
            {
                "Type": "CYLINDER",
                "Location": [ -2.006, 0, 0.406 ],
                "Axis": [ 1, 0, 0 ],
                "Radius": 0.02,
                "Length": 0.6
            }
        ]
    }
}
