{
    "Name": "HMMWV DoubleWishbone Front",
    "Type": "Suspension",
    "Template": "DoubleWishbone",

    "Vehicle-Frame Inertia": false,

    "Camber Angle (deg)": 0,
    "Toe Angle (deg)": 0,

    "Spindle": {
        "Mass": 14.705,
        "COM": [ -0.040, 0.910, -0.026 ],
        "Inertia": [ 0.04117, 0.07352, 0.04117 ],
        "Radius": 0.15,
        "Width": 0.06
    },

    "Upright": {
        "Mass": 19.450,
        "COM": [ -0.040, 0.751, -0.026 ],
        "Moments of Inertia": [ 0.1656, 0.1934, 0.04367 ],
        "Products of Inertia": [ 0, 0, 0 ],
        "Radius": 0.04
    },

    // If bushing data is defined, use bushings for connectino to chassis.
    // Otherwise, use revolute joints.
    "Upper Control Arm": {
        "Mass": 5.813,
        "COM": [ -0.106, 0.589, 0.218 ],
        "Moments of Inertia": [ 0.03, 0.03, 0.06276 ],
        "Products of Inertia": [ 0, 0, 0 ],
        "Radius": 0.02,
        "Location Upright": [ -0.053, 0.716, 0.215 ],
        "Location Chassis Front": [ -0.048, 0.446, 0.245 ],
        "Location Chassis Back": [ -0.268, 0.478, 0.196 ],
        "Bushing Data": {
            "Stiffness Linear": 7e7,
            "Damping Linear": 0.35e5,
            "Stiffness Rotational": 1e5,
            "Damping Rotational": 0.5e3,
            "DOF": {
                "Stiffness Linear": 0,
                "Damping Linear": 0,
                "Stiffness Rotational": 0,
                "Damping Rotational": 0
            }
        }
    },

    // If bushing data is defined, use bushings for connectino to chassis.
    // Otherwise, use revolute joints.
    "Lower Control Arm": {
        "Mass": 23.965,
        "COM": [ 0.000, 0.547, -0.059 ],
        "Moments of Inertia": [ 0.4, 0.4, 0.8938 ],
        "Products of Inertia": [ 0, 0, 0 ],
        "Radius": 0.03,
        "Location Upright": [ -0.036, 0.787, -0.118 ],
        "Location Chassis Front": [ 0.223, 0.307, 0.000 ],
        "Location Chassis Back": [ -0.223, 0.307, 0.000 ],
        "Bushing Data": {
            "Stiffness Linear": 7e7,
            "Damping Linear": 0.35e5,
            "Stiffness Rotational": 1e5,
            "Damping Rotational": 0.5e3,
            "DOF": {
                "Stiffness Linear": 0,
                "Damping Linear": 0,
                "Stiffness Rotational": 0,
                "Damping Rotational": 0
            }
        }
    },

    // If mass, inertia, and radius are defined, use bodies to model tierods.
    // Otherwise, use distance constraints.
    "Tierod": {
        "Mass": 6,
        "Radius": 0.02,
        "Inertia": [ 0.05, 0.05, 0.5 ],
        "Location Chassis": [ -0.250, 0.448, 0.054 ],
        "Location Upright": [ -0.176, 0.821, -0.016 ]
    },

    "Spring": {
        "Location Chassis": [ 0.104, 0.510, 0.197 ],
        "Location Arm": [ 0.097, 0.543, -0.047 ],
        "Minimum Length": 0.15,
        "Maximum Length": 0.3,
        "Spring Curve Data": [
            [ -0.2, -322095.536 ],
            [ -0.18, -240521.166 ],
            [ -0.16, -174535.686 ],
            [ -0.14, -122406.996 ],
            [ -0.12, -82402.997 ],
            [ -0.1, -52791.592 ],
            [ -0.08, -31840.681 ],
            [ -0.06, -17818.165 ],
            [ -0.04, -8991.945 ],
            [ -0.02, -3629.923 ],
            [ 0, 0 ],
            [ 0.02, 3629.923 ],
            [ 0.04, 8991.945 ],
            [ 0.06, 17818.165 ],
            [ 0.08, 31840.681 ],
            [ 0.1, 52791.592 ],
            [ 0.12, 82402.997 ],
            [ 0.14, 122406.996 ],
            [ 0.16, 174535.686 ],
            [ 0.18, 240521.166 ],
            [ 0.2, 322095.536 ]
        ],
        "Free Length": 0.339
    },

    "Shock": {
        "Location Chassis": [ 0.104, 0.498, 0.323 ],
        "Location Arm": [ 0.097, 0.543, -0.047 ],
        "Damping Coefficient": 19015.5692
    },

    "Axle": {
        "Inertia": 0.4
    }
}
